[
    {
        "title": "iPhone 11 Pro\n64 GB",
        "price": null,
        "imageUrl": "https://www.magpiehq.com/developer-challenge/smartphones//images/iphone-11-pro.png",
        "capacityMB": null,
        "colour": "Green",
        "availabilityText": "",
        "isAvailable": false,
        "shippingText": "Availability: Out of Stock",
        "shippingDate": null
    },
    {
        "title": "iPhone 11\n64GB",
        "price": null,
        "imageUrl": "https://www.magpiehq.com/developer-challenge/smartphones//images/iphone-11.png",
        "capacityMB": null,
        "colour": "Black",
        "availabilityText": "",
        "isAvailable": false,
        "shippingText": "Unavailable for delivery",
        "shippingDate": null
    },
    {
        "title": "iPhone 11\n64GB",
        "price": null,
        "imageUrl": "https://www.magpiehq.com/developer-challenge/smartphones//images/iphone-11.png",
        "capacityMB": null,
        "colour": "White",
        "availabilityText": "",
        "isAvailable": false,
        "shippingText": "Unavailable for delivery",
        "shippingDate": null
    },
    {
        "title": "iPhone 12 Pro Max\n128GB",
        "price": null,
        "imageUrl": "https://www.magpiehq.com/developer-challenge/smartphones//images/iphone-12-pro.png",
        "capacityMB": null,
        "colour": "Sky Blue",
        "availabilityText": "",
        "isAvailable": false,
        "shippingText": "Delivery by 2024-09-30",
        "shippingDate": null
    },
    {
        "title": "Samsung Galaxy S20\n128GB",
        "price": null,
        "imageUrl": "https://www.magpiehq.com/developer-challenge/smartphones//images/s-20.png",
        "capacityMB": null,
        "colour": "Grey",
        "availabilityText": "",
        "isAvailable": false,
        "shippingText": "Available on 6 Oct 2024",
        "shippingDate": null
    },
    {
        "title": "Huawei P30 Pro\n128GB",
        "price": null,
        "imageUrl": "https://www.magpiehq.com/developer-challenge/smartphones//images/p-30.png",
        "capacityMB": null,
        "colour": "Black",
        "availabilityText": "",
        "isAvailable": false,
        "shippingText": "Free Shipping",
        "shippingDate": null
    },
    {
        "title": "Nokia 3310\n100MB",
        "price": null,
        "imageUrl": "https://www.magpiehq.com/developer-challenge/smartphones//images/nokia-3310.png",
        "capacityMB": null,
        "colour": "Orange",
        "availabilityText": "",
        "isAvailable": false,
        "shippingText": "Delivery from 29 Oct 2024",
        "shippingDate": null
    },
    {
        "title": "Nokia 3310\n100MB",
        "price": null,
        "imageUrl": "https://www.magpiehq.com/developer-challenge/smartphones//images/nokia-3310.png",
        "capacityMB": null,
        "colour": "Yellow",
        "availabilityText": "",
        "isAvailable": false,
        "shippingText": "Delivery from 29 Oct 2024",
        "shippingDate": null
    },
    {
        "title": "Nokia 3310\n100MB",
        "price": null,
        "imageUrl": "https://www.magpiehq.com/developer-challenge/smartphones//images/nokia-3310.png",
        "capacityMB": null,
        "colour": "Grey",
        "availabilityText": "",
        "isAvailable": false,
        "shippingText": "Delivery from 29 Oct 2024",
        "shippingDate": null
    },
    {
        "title": "Nokia 3310\n100MB",
        "price": null,
        "imageUrl": "https://www.magpiehq.com/developer-challenge/smartphones//images/nokia-3310.png",
        "capacityMB": null,
        "colour": "Blue",
        "availabilityText": "",
        "isAvailable": false,
        "shippingText": "Delivery from 29 Oct 2024",
        "shippingDate": null
    }
]